<annotation>
	<folder>train</folder>
	<filename>Glass (16).jpg</filename>
	<path>C:\1_pychamproject\work\models\research\object_detection\images\train\Glass (16).jpg</path>
	<source>
		<database>Unknown</database>
	</source>
	<size>
		<width>636</width>
		<height>472</height>
		<depth>3</depth>
	</size>
	<segmented>0</segmented>
	<object>
		<name>Glass</name>
		<pose>Unspecified</pose>
		<truncated>0</truncated>
		<difficult>0</difficult>
		<bndbox>
			<xmin>223</xmin>
			<ymin>52</ymin>
			<xmax>340</xmax>
			<ymax>381</ymax>
		</bndbox>
	</object>
</annotation>
